LICENSE.md
MANIFEST.in
README.md
setup.cfg
setup.py
game/__init__.py
game/animations/__init__.py
game/animations/circle_player_initial_animation.py
game/animations/litter_bounce.py
game/animations/obstacle_pulsing_animation.py
game/animations/particle_fade_animation.py
game/animations/player_bounce.py
game/animations/power_up_fade_out.py
game/animations/text_up_fade_out_animation.py
game/assets/__init__.py
game/assets/fonts/__init__.py
game/game_objects/__init__.py
game/game_objects/controllers/__init__.py
game/game_objects/controllers/background_particles_controller.py
game/game_objects/controllers/items_controller_wrapper.py
game/game_objects/controllers/main_menu_controller.py
game/game_objects/controllers/main_scene_controller.py
game/game_objects/controllers/obstacle_controller_wrapper.py
game/game_objects/controllers/pause_controller.py
game/game_objects/controllers/player_controller.py
game/game_objects/controllers/retry_controller.py
game/game_objects/controllers/score_controller.py
game/game_objects/controllers/test_rect_generator.py
game/game_objects/controllers/items_controller/__init__.py
game/game_objects/controllers/items_controller/invencible_power_up_controller.py
game/game_objects/controllers/items_controller/star_score_controller.py
game/game_objects/controllers/obstacles_controllers/__init__.py
game/game_objects/controllers/obstacles_controllers/half_moon_spinning_rect_obstacle_controller.py
game/game_objects/controllers/obstacles_controllers/invisible_middle_obstacle_controller.py
game/game_objects/controllers/obstacles_controllers/invisible_simple_obstacle_controller.py
game/game_objects/controllers/obstacles_controllers/middle_rect_obstacle_controller.py
game/game_objects/controllers/obstacles_controllers/random_x_final_obstacle_controller.py
game/game_objects/controllers/obstacles_controllers/rect_translate_x_obstacle_cotroller.py
game/game_objects/controllers/obstacles_controllers/simple_obstacle_controller.py
pygame_engine.egg-info/PKG-INFO
pygame_engine.egg-info/SOURCES.txt
pygame_engine.egg-info/dependency_links.txt
pygame_engine.egg-info/requires.txt
pygame_engine.egg-info/top_level.txt