Metadata-Version: 2.1
Name: pygame-engine
Version: 0.0.4.dev0
Summary: Simple pygame game engine.
Home-page: https://github.com/CarlosMatheus/Engine
Author: Aloysio, Carlos, Igor
Author-email: aloysiogl@gmail.com
License: MIT
Project-URL: Wiki, https://github.com/CarlosMatheus/Engine/wiki
Project-URL: Source, https://github.com/CarlosMatheus/Engine
Keywords: engine pygame
Platform: UNKNOWN
Classifier: Development Status :: 3 - Alpha
Classifier: Intended Audience :: Developers
Classifier: Topic :: Games/Entertainment
Classifier: License :: OSI Approved :: MIT License
Classifier: Programming Language :: Python :: 3.5
Provides-Extra: test
